hivemind_persona/__init__.py
hivemind_persona/__main__.py
hivemind_persona/version.py
hivemind_persona-0.0.2.dist-info/LICENSE.md
hivemind_persona-0.0.2.dist-info/METADATA
hivemind_persona-0.0.2.dist-info/WHEEL
hivemind_persona-0.0.2.dist-info/entry_points.txt
hivemind_persona-0.0.2.dist-info/top_level.txt
hivemind_persona-0.0.2.dist-info/RECORD
