Metadata-Version: 2.1
Name: hivemind-persona
Version: 0.0.2
Summary: replace ovos-core with ovos-persona in your hivemind listener
Home-page: https://github.com/JarbasHiveMind/hivemind-persona
Author: jarbasAi
Author-email: jarbasai@mailfence.com
License: Apache-2.0
Platform: UNKNOWN
Requires-Dist: hivemind-core<2.0.0,>=1.0.0
Requires-Dist: ovos-persona
Requires-Dist: click
